[{"cids_pri": [{"co_cid": "C690", "no_cid": "Neoplasia maligna da conjuntiva"}, {"co_cid": "D210", "no_cid": "Neoplasia benigna do tecido conjuntivo e outros tecidos moles da cabeça, face e pescoço"}, {"co_cid": "H119", "no_cid": "Transtorno não especificado da conjuntiva"}], "co_proc_formatado": "02.01.01.009-7", "co_procedimento": "0201010097", "co_rubrica": "", "ds_complexidade": "Média Complexidade", "ds_financiamento": "Média e Alta Complexidade (MAC)", "ds_sexo": "Indiferente/Ambos", "no_procedimento": "Biopsia De Conjuntiva", "qt_dias_permanencia": "Não se aplica", "qt_maxima_execucao": "2", "qt_pontos": 0, "qt_tempo_permanencia": "Não se aplica", "tp_registros": [{"no_registro": "BPA (Individualizado)"}, {"no_registro": "AIH (Proc. Especial)"}], "vl_idade_maxima": "130 Anos", "vl_idade_minima": "0 Anos", "vl_sa": "R$ 31,10", "vl_sh": "R$ 31,10", "vl_sp": "R$ 0,00"}]