[{"cids_pri": [{"co_cid": "L105", "no_cid": "Pênfigo induzido por drogas"}, {"co_cid": "L123", "no_cid": "Epidermólise bolhosa adquirida"}, {"co_cid": "L138", "no_cid": "Outras afecções bolhosas especificadas"}, {"co_cid": "L200", "no_cid": "Prurigo de besnier"}, {"co_cid": "L208", "no_cid": "Outras dermatites atópicas"}, {"co_cid": "L209", "no_cid": "Dermatite atópica, não especificada"}, {"co_cid": "L210", "no_cid": "Seborréia do couro cabeludo"}, {"co_cid": "L211", "no_cid": "Dermatite seborréica infantil"}, {"co_cid": "L218", "no_cid": "Outras dermatites seborréicas"}, {"co_cid": "L219", "no_cid": "Dermatite seborréica, não especificada"}, {"co_cid": "L22", "no_cid": "Dermatite das fraldas"}, {"co_cid": "L230", "no_cid": "Dermatite alérgica de contato devida a metais"}, {"co_cid": "L231", "no_cid": "Dermatite alérgica de contato devida a adesivos"}, {"co_cid": "L232", "no_cid": "Dermatite alérgica de contato devida a cosméticos"}, {"co_cid": "L233", "no_cid": "Dermatite alérgica de contato devido a drogas em contato com a pele"}, {"co_cid": "L234", "no_cid": "Dermatite alérgica de contato devida a corantes"}, {"co_cid": "L235", "no_cid": "Dermatite alérgica de contato devida a outros produtos químicos"}, {"co_cid": "L236", "no_cid": "Dermatite alérgica de contato devida a alimentos em contato com a pele"}, {"co_cid": "L237", "no_cid": "Dermatite alérgica de contato devido a plantas, exceto alimentos"}, {"co_cid": "L238", "no_cid": "Dermatite alérgica de contato devido a outros agentes"}, {"co_cid": "L239", "no_cid": "Dermatite alérgica de contato, de causa não especificada"}, {"co_cid": "L240", "no_cid": "Dermatite de contato por irritantes devida a detergentes"}, {"co_cid": "L241", "no_cid": "Dermatite de contato por irritantes devido a óleos e gorduras"}, {"co_cid": "L242", "no_cid": "Dermatite de contato por irritantes devida a solventes"}, {"co_cid": "L243", "no_cid": "Dermatite de contato por irritantes devida a cosméticos"}, {"co_cid": "L244", "no_cid": "Dermatite de contato por irritantes devida a drogas em contato com a pele"}, {"co_cid": "L245", "no_cid": "Dermatite de contato por irritantes devida a outros produtos químicos"}, {"co_cid": "L246", "no_cid": "Dermatite de contato por irritantes devida a alimentos em contato com a pele"}, {"co_cid": "L247", "no_cid": "Dermatite de contato por irritantes devido a plantas, exceto alimentos"}, {"co_cid": "L248", "no_cid": "Dermatite de contato por irritantes devido a outros agentes"}, {"co_cid": "L249", "no_cid": "Dermatite de contato por irritantes, de causa não especificada"}, {"co_cid": "L250", "no_cid": "Dermatite de contato não especificada devida a cosméticos"}, {"co_cid": "L251", "no_cid": "Dermatite de contato não especificada devida a drogas em contato com a pele"}, {"co_cid": "L252", "no_cid": "Dermatite de contato não especificada devida a corantes"}, {"co_cid": "L253", "no_cid": "Dermatite de contato não especificada devida a outros produtos químicos"}, {"co_cid": "L254", "no_cid": "Dermatite de contato não especificada devida a alimentos em contato com a pele"}, {"co_cid": "L255", "no_cid": "Dermatite de contato não especificada devida a plantas, exceto alimentos"}, {"co_cid": "L258", "no_cid": "Dermatite de contato não especificada devida a outros agentes"}, {"co_cid": "L259", "no_cid": "Dermatite de contato não especificada, de causa não especificada"}, {"co_cid": "L26", "no_cid": "Dermatite esfoliativa"}, {"co_cid": "L272", "no_cid": "Dermatite devida à ingestão de alimentos"}, {"co_cid": "L278", "no_cid": "Dermatite devida a outras substâncias de uso interno"}, {"co_cid": "L279", "no_cid": "Dermatite devida a substância não especificada de uso interno"}, {"co_cid": "L280", "no_cid": "Líquen simples crônico"}, {"co_cid": "L281", "no_cid": "Prurigo nodular"}, {"co_cid": "L282", "no_cid": "Outras formas de prurigo"}, {"co_cid": "L290", "no_cid": "Prurido anal"}, {"co_cid": "L291", "no_cid": "Prurido escrotal"}, {"co_cid": "L292", "no_cid": "Prurido vulvar"}, {"co_cid": "L293", "no_cid": "Prurido anogenital, não especificado"}, {"co_cid": "L298", "no_cid": "Outras formas de prurido"}, {"co_cid": "L299", "no_cid": "Prurido não especificado"}, {"co_cid": "L300", "no_cid": "Dermatite numular"}, {"co_cid": "L301", "no_cid": "Disidrose [Pompholyx]"}, {"co_cid": "L302", "no_cid": "Autossensibilização cutânea"}, {"co_cid": "L303", "no_cid": "Dermatite infectada"}, {"co_cid": "L304", "no_cid": "Intertrigo eritematoso"}, {"co_cid": "L305", "no_cid": "Pitiríase alba"}, {"co_cid": "L308", "no_cid": "Outras dermatites especificadas"}, {"co_cid": "L309", "no_cid": "Dermatite não especificada"}, {"co_cid": "L432", "no_cid": "Reação liquenóide a droga"}, {"co_cid": "L500", "no_cid": "Urticária alérgica"}, {"co_cid": "L508", "no_cid": "Outras urticárias"}, {"co_cid": "L512", "no_cid": "Necrólise epidérmica tóxica [síndrome de lyell]"}], "co_proc_formatado": "03.03.08.005-1", "co_procedimento": "0303080051", "co_rubrica": "", "ds_complexidade": "Média Complexidade", "ds_financiamento": "Média e Alta Complexidade (MAC)", "ds_sexo": "Indiferente/Ambos", "no_procedimento": "Tratamento De Dermatites E Eczemas", "qt_dias_permanencia": "3", "qt_maxima_execucao": "1", "qt_pontos": 100, "qt_tempo_permanencia": "Não se aplica", "tp_registros": [{"no_registro": "AIH (Proc. Principal)"}], "vl_idade_maxima": "18 Anos", "vl_idade_minima": "0 Anos", "vl_sa": "R$ 0,00", "vl_sh": "R$ 191,85", "vl_sp": "R$ 33,06"}]