[{"cids_pri": [{"co_cid": "E40", "no_cid": "Kwashiorkor"}, {"co_cid": "E41", "no_cid": "Marasmo nutricional"}, {"co_cid": "E42", "no_cid": "Kwashiorkor marasmático"}, {"co_cid": "E43", "no_cid": "Desnutrição protéico-calórica grave não especificada"}, {"co_cid": "E440", "no_cid": "Desnutrição protéico-calórica moderada"}, {"co_cid": "E441", "no_cid": "Desnutrição protéico-calórica leve"}, {"co_cid": "E45", "no_cid": "Atraso do desenvolvimento devido à desnutrição protéico-calórica"}, {"co_cid": "E46", "no_cid": "Desnutrição protéico-calórica não especificada"}], "co_proc_formatado": "03.03.03.002-0", "co_procedimento": "0303030020", "co_rubrica": "", "ds_complexidade": "Média Complexidade", "ds_financiamento": "Média e Alta Complexidade (MAC)", "ds_sexo": "Indiferente/Ambos", "no_procedimento": "Tratamento De Desnutricao", "qt_dias_permanencia": "6", "qt_maxima_execucao": "1", "qt_pontos": 80, "qt_tempo_permanencia": "Não se aplica", "tp_registros": [{"no_registro": "AIH (Proc. Principal)"}], "vl_idade_maxima": "130 Anos", "vl_idade_minima": "0 Anos", "vl_sa": "R$ 0,00", "vl_sh": "R$ 374,26", "vl_sp": "R$ 72,52"}]