[{"cids_pri": [{"co_cid": "H018", "no_cid": "Outras inflamações especificadas da pálpebra"}, {"co_cid": "H040", "no_cid": "Dacrioadenite"}, {"co_cid": "H043", "no_cid": "Inflamação aguda e não especificada dos canais lacrimais"}, {"co_cid": "H050", "no_cid": "Inflamação aguda da órbita"}, {"co_cid": "H055", "no_cid": "Corpo estranho (antigo) retido conseqüente a ferimento perfurante da órbita"}, {"co_cid": "H150", "no_cid": "Esclerite"}, {"co_cid": "H160", "no_cid": "Úlcera de córnea"}, {"co_cid": "H301", "no_cid": "Inflamação corrorretiniana disseminada"}, {"co_cid": "H302", "no_cid": "Ciclite posterior"}, {"co_cid": "H308", "no_cid": "Outras inflamações coriorretinianas"}, {"co_cid": "H309", "no_cid": "Inflamação não especificada da coróide e da retina"}, {"co_cid": "H440", "no_cid": "Endoftalmite purulenta"}, {"co_cid": "H441", "no_cid": "Outras endoftalmites"}, {"co_cid": "H451", "no_cid": "Endoftalmite em doenças classificadas em outra parte"}], "co_proc_formatado": "03.03.05.014-4", "co_procedimento": "0303050144", "co_rubrica": "", "ds_complexidade": "Média Complexidade", "ds_financiamento": "Média e Alta Complexidade (MAC)", "ds_sexo": "Indiferente/Ambos", "no_procedimento": "Tratamento Clínico De Intercorrências Oftalmológicas De Origem Infecciosa", "qt_dias_permanencia": "5", "qt_maxima_execucao": "Não se aplica", "qt_pontos": 120, "qt_tempo_permanencia": "Não se aplica", "tp_registros": [{"no_registro": "AIH (Proc. Principal)"}], "vl_idade_maxima": "130 Anos", "vl_idade_minima": "0 Anos", "vl_sa": "R$ 0,00", "vl_sh": "R$ 240,05", "vl_sp": "R$ 40,22"}]