[{"cids_pri": [{"co_cid": "T369", "no_cid": "Intoxicação por antibióticos sistêmicos não especificados"}, {"co_cid": "T379", "no_cid": "Intoxicação por agentes antiinfecciosos e antiparasitários sistêmicos não especificados"}, {"co_cid": "T389", "no_cid": "Intoxicação por outros antagonistas hormonais, e os não especificados"}, {"co_cid": "T399", "no_cid": "Intoxicação por analgésico não-opiáceo, antipirético e anti-reumático, não especificados"}, {"co_cid": "T409", "no_cid": "Intoxicação por outros psicodislépticos e os não especificados [alucinógenos]"}, {"co_cid": "T428", "no_cid": "Intoxicação por drogas antiparkinsonianos e outros depressores centrais do tônus muscular"}, {"co_cid": "T439", "no_cid": "Intoxicação por droga psicotrópica não especificada"}, {"co_cid": "T448", "no_cid": "Intoxicação por bloquead. neuronais adrenérgicos e de ação central, não class. noutra parte"}, {"co_cid": "T449", "no_cid": "Intoxicação por out. drogas que afetam princ. o sist. nervoso autônomo e as ñ especificadas"}, {"co_cid": "T459", "no_cid": "Intoxicação por substância essencialmente sistêmica e hematológica não especificada"}, {"co_cid": "T460", "no_cid": "Intoxicação por glicosídeos estimulantes do coração e substâncias de ação semelhante"}, {"co_cid": "T468", "no_cid": "Intoxicação por drogas antivaricosas, incluindo substâncias esclerosantes"}, {"co_cid": "T469", "no_cid": "Intoxicação por outras subst. e as não especificada que agem essenc. sobre o aparelho circulatório"}, {"co_cid": "T479", "no_cid": "Intoxicação por substância não especificada que atua primariamente sobre o aparelho gastrointestinal"}, {"co_cid": "T487", "no_cid": "Intoxicação por outras substâncias e as não espec. que atuam primar. sobre o aparelho respiratório"}, {"co_cid": "T509", "no_cid": "Intoxicação por outras drogas, medicamentos e substâncias biológicas e as não especificadas"}, {"co_cid": "T519", "no_cid": "Efeito tóxico de álcool não especificado"}, {"co_cid": "T529", "no_cid": "Efeito tóxico de solvente orgânico não especificado"}, {"co_cid": "T539", "no_cid": "Efeito tóxico de derivados halogênicos de hidrocarbonetos alifáticos e aromáticos não especificados"}, {"co_cid": "T549", "no_cid": "Efeito tóxico de substância corrosiva não especificada"}, {"co_cid": "T55", "no_cid": "Efeito tóxico de sabões e detergentes"}, {"co_cid": "T579", "no_cid": "Efeito tóxico de substância inorgânica não especificada"}, {"co_cid": "T609", "no_cid": "Efeito tóxico de pesticida não especificado"}, {"co_cid": "T619", "no_cid": "Efeito tóxico de frutos do mar não especificados"}, {"co_cid": "T629", "no_cid": "Efeito tóxico de substâncias nocivas ingeridas como alimento, não especificadas"}, {"co_cid": "T639", "no_cid": "Efeito tóxico de contato com animal venenoso não especificado"}, {"co_cid": "T64", "no_cid": "Efeito tóxico da aflatoxina e de outras micotoxinas contaminantes de alimentos"}, {"co_cid": "T659", "no_cid": "Efeito tóxico de substância não especificada"}], "co_proc_formatado": "03.08.02.001-4", "co_procedimento": "0308020014", "co_rubrica": "", "ds_complexidade": "Alta Complexidade", "ds_financiamento": "Média e Alta Complexidade (MAC)", "ds_sexo": "Indiferente/Ambos", "no_procedimento": "Hemodiafiltracao Continua", "qt_dias_permanencia": "Não se aplica", "qt_maxima_execucao": "Não se aplica", "qt_pontos": 0, "qt_tempo_permanencia": "Não se aplica", "tp_registros": [{"no_registro": "AIH (Proc. Especial)"}], "vl_idade_maxima": "130 Anos", "vl_idade_minima": "0 Anos", "vl_sa": "R$ 0,00", "vl_sh": "R$ 107,96", "vl_sp": "R$ 0,00"}]