[{"cids_pri": [{"co_cid": "S424", "no_cid": "Fratura da extremidade inferior do úmero"}, {"co_cid": "S520", "no_cid": "Fratura da extremidade superior do cúbito [ulna]"}, {"co_cid": "S521", "no_cid": "Fratura da extremidade superior do rádio"}, {"co_cid": "S522", "no_cid": "Fratura da diáfise do cúbito [ulna]"}, {"co_cid": "S527", "no_cid": "Fraturas múltiplas do antebraço"}, {"co_cid": "S528", "no_cid": "Fratura de outras partes do antebraço"}, {"co_cid": "S529", "no_cid": "Fratura do antebraço, parte não especificada"}, {"co_cid": "S530", "no_cid": "Luxação da cabeça do rádio"}, {"co_cid": "S531", "no_cid": "Luxação do cotovelo, não especificada"}, {"co_cid": "S532", "no_cid": "Ruptura traumática do ligamento colateral do rádio"}, {"co_cid": "S533", "no_cid": "Ruptura traumática do ligamento colateral do cúbito [ulna]"}, {"co_cid": "S534", "no_cid": "Entorse e distensão do cotovelo"}, {"co_cid": "T112", "no_cid": "Luxação, entorse e distensão de artic. e ligam. ñ especif. de membro superior, nível ñ especificado"}], "co_proc_formatado": "04.08.02.015-6", "co_procedimento": "0408020156", "co_rubrica": "", "ds_complexidade": "Média Complexidade", "ds_financiamento": "Média e Alta Complexidade (MAC)", "ds_sexo": "Indiferente/Ambos", "no_procedimento": "Redução Incruenta De Fratura / Lesão Fisaria De Cotovelo", "qt_dias_permanencia": "2", "qt_maxima_execucao": "2", "qt_pontos": 100, "qt_tempo_permanencia": "Não se aplica", "tp_registros": [{"no_registro": "BPA (Individualizado)"}, {"no_registro": "AIH (Proc. Principal)"}], "vl_idade_maxima": "130 Anos", "vl_idade_minima": "0 Anos", "vl_sa": "R$ 0,00", "vl_sh": "R$ 75,68", "vl_sp": "R$ 76,69"}]